fency_pgn-0.2.1.dist-info/METADATA
fency_pgn-0.2.1.dist-info/WHEEL
fency_pgn/__init__.py
fency_pgn/fency_pgn.abi3.so
fency_pgn-0.2.1.dist-info/RECORD
